schema_registry/__init__.py
schema_registry/app/__init__.py
schema_registry/app/business/__init__.py
schema_registry/app/business/cli.py
schema_registry/app/ui/__init__.py
schema_registry/app/ui/cli.py
schema_registry/app/ui/registry.py
schema_registry/config.py
schema_registry/registries/HttpRegistry.py
schema_registry/registries/__init__.py
schema_registry/registries/entities.py
schema_registry-0.0.6.dist-info/entry_points.txt
schema_registry-0.0.6.dist-info/LICENSE
schema_registry-0.0.6.dist-info/WHEEL
schema_registry-0.0.6.dist-info/METADATA
schema_registry-0.0.6.dist-info/RECORD
